cprints/__init__.py
cprints/config.py
cprints/main.py
cprints-1.0.7.dist-info/LICENSE
cprints-1.0.7.dist-info/METADATA
cprints-1.0.7.dist-info/WHEEL
cprints-1.0.7.dist-info/top_level.txt
cprints-1.0.7.dist-info/RECORD
