Metadata-Version: 2.1
Name: cprints
Version: 1.0.7
Summary: 输出彩色文字
Home-page: https://github.com/PengKe-x/cprins
Author: PengKe
Author-email: 925330867@qq.com
Classifier: Programming Language :: Python :: 3
Classifier: License :: OSI Approved :: MIT License
Classifier: Operating System :: OS Independent
Requires-Python: >=3.6
License-File: LICENSE
